{
  "": "",
  "throw error": "throw error",
  "toggle": "toggle",
  "Аватар": "Аватар",
  "Валюта": "Валюта",
  "Ваш возраст": "Ваш возраст",
  "Ваша фамилия": "Ваша фамилия",
  "Ваше возраст": "Ваше возраст",
  "Ваше имя": "Ваше имя",
  "Ваше фамилия": "Ваше фамилия",
  "Введите username": "Введите username",
  "Введите имя пользователя": "Введите имя пользователя",
  "Введите пароль": "Введите пароль",
  "Введите ссылку на аватар": "Введите ссылку на аватар",
  "Войти": "Войти",
  "Выйти": "Выйти",
  "Главная": "Главная",
  "Город": "Город",
  "Данные не указаны": "Данные не указаны",
  "Имя и фамилия обязательны": "Имя и фамилия обязательны",
  "Имя пользователя": "Имя пользователя",
  "Некорректная страна": "Некорректная страна",
  "Некорректный возраст": "Некорректный возраст",
  "О Сайте": "О Сайте",
  "О нас": "О нас",
  "О сайте": "О сайте",
  "Отмена": "Отмена",
  "Попробоуйте обновить страницу": "Попробоуйте обновить страницу",
  "Попробуйте обновить страницу": "Попробуйте обновить страницу",
  "Ппробоуйте обновить страницу": "Ппробоуйте обновить страницу",
  "Произошла непредвиденная ошибка": "Произошла непредвиденная ошибка",
  "Произошла ошибка": "Произошла ошибка",
  "Произошла ошибка при загрузке профиля": "Произошла ошибка при загрузке профиля",
  "Профиль": "Профиль",
  "Редактировать": "Редактировать",
  "Серверная ошибка": "Серверная ошибка",
  "Сохранить": "Сохранить",
  "Страна": "Страна",
  "Страница не найдена": "Страница не найдена",
  "Укажите валюту": "Укажите валюту",
  "Укажите страну": "Укажите страну",
  "Фамилия": "Фамилия",
  "Форма авторизации": "Форма авторизации",
  "Язык": "Язык",
  "какой то русский текст": "какой то русский текст"
}
